vitax_rag/__init__.py
vitax_rag/cli.py
vitax_rag/tree.py
vitax_rag/utils.py
vitax_rag/lca/tree.py
vitax_rag/model/model_hyena.py
vitax_rag/model/model_vitax.py
vitax_rag/model/tokenizer_hyena.py
vitax_rag/model/hyena/huggingface.py
vitax_rag/model/hyena/standalone_hyenadna.py
vitax_rag/model/hyena/train.py
vitax_rag/model/hyena/csrc/fftconv/launch_fftconv.py
vitax_rag/model/hyena/csrc/fftconv/lut_code_gen.py
vitax_rag/model/hyena/csrc/fftconv/setup.py
vitax_rag/model/hyena/evals/hg38_inference.py
vitax_rag/model/hyena/evals/hg38_inference_decoder.py
vitax_rag/model/hyena/evals/instruction_tuned_genomics.py
vitax_rag/model/hyena/evals/soft_prompting_genomics.py
vitax_rag/model/hyena/src/callbacks/gpu_affinity.py
vitax_rag/model/hyena/src/callbacks/norms.py
vitax_rag/model/hyena/src/callbacks/params.py
vitax_rag/model/hyena/src/callbacks/progressive_resizing.py
vitax_rag/model/hyena/src/callbacks/seqlen_warmup_reload.py
vitax_rag/model/hyena/src/callbacks/timer.py
vitax_rag/model/hyena/src/callbacks/wandb.py
vitax_rag/model/hyena/src/dataloaders/__init__.py
vitax_rag/model/hyena/src/dataloaders/base.py
vitax_rag/model/hyena/src/dataloaders/et.py
vitax_rag/model/hyena/src/dataloaders/fault_tolerant_sampler.py
vitax_rag/model/hyena/src/dataloaders/genomics.py
vitax_rag/model/hyena/src/dataloaders/datasets/chromatin_profile_dataset.py
vitax_rag/model/hyena/src/dataloaders/datasets/genomic_bench_dataset.py
vitax_rag/model/hyena/src/dataloaders/datasets/hg38_char_tokenizer.py
vitax_rag/model/hyena/src/dataloaders/datasets/hg38_dataset.py
vitax_rag/model/hyena/src/dataloaders/datasets/hg38_fixed_dataset.py
vitax_rag/model/hyena/src/dataloaders/datasets/hg38_icl_dataset.py
vitax_rag/model/hyena/src/dataloaders/datasets/icl_genomics_dataset.py
vitax_rag/model/hyena/src/dataloaders/datasets/lm_dataset.py
vitax_rag/model/hyena/src/dataloaders/datasets/nucleotide_transformer_dataset.py
vitax_rag/model/hyena/src/dataloaders/datasets/species_dataset.py
vitax_rag-0.2.1.dist-info/METADATA
vitax_rag-0.2.1.dist-info/WHEEL
vitax_rag-0.2.1.dist-info/entry_points.txt
vitax_rag-0.2.1.dist-info/top_level.txt
vitax_rag-0.2.1.dist-info/RECORD
