Metadata-Version: 2.4
Name: vitax-rag
Version: 0.2.1
Summary: ViTax-RAG: Alignment-augmented language model for viral taxonomy classification
Author-email: Peak Zhou <your_email@xxx.edu>
License: MIT
Requires-Python: >=3.8
Requires-Dist: torch>=1.12
Requires-Dist: numpy>=1.21
Requires-Dist: scikit-learn<2.0,>=1.0
Requires-Dist: pandas<3.0,>=1.3
Requires-Dist: biopython>=1.80
Requires-Dist: tqdm>=4.60
Requires-Dist: torchvision
Requires-Dist: transformers<5.0,>=4.26
Requires-Dist: tokenizers<0.16,>=0.13
Requires-Dist: einops>=0.6
Requires-Dist: omegaconf>=2.2
Requires-Dist: hydra-core>=1.2
